{
  "parent": "minecraft:recipes/root",
  "rewards": {
    "recipes": [
      "mytutorial:firstblock"
    ]
  },
  "criteria": {
    "cobblestone": {
      "trigger": "minecraft:inventory_changed",
      "conditions": {
        "items": [
          {
            "item": "minecraft:cobblestone"
          }
        ]
      }
    },
    "has_the_recipe": {
      "trigger": "minecraft:recipe_unlocked",
      "conditions": {
        "recipe": "mytutorial:firstblock"
      }
    }
  },
  "requirements": [
    [
      "cobblestone",
      "has_the_recipe"
    ]
  ]
}